setup.py
tomthumb/__init__.py
tomthumb/__main__.py
tomthumb/thumbnail.py
tomthumb.egg-info/PKG-INFO
tomthumb.egg-info/SOURCES.txt
tomthumb.egg-info/dependency_links.txt
tomthumb.egg-info/entry_points.txt
tomthumb.egg-info/requires.txt
tomthumb.egg-info/top_level.txt