Metadata-Version: 1.0
Name: tomthumb
Version: 0.0.1
Summary: A handy document thumbnailing tool.
Home-page: https://github.com/bcoe/Adventures-in-Document-Thumbnailing
Author: Benjamin Coe
Author-email: bencoe@gmail.com
License: UNKNOWN
Platform: UNKNOWN
